README.md
setup.py
./pyp-runner.py
pyp/__init__.py
pyp/__main__.py
pyp/pyp.py
pyp_manager.egg-info/PKG-INFO
pyp_manager.egg-info/SOURCES.txt
pyp_manager.egg-info/dependency_links.txt
pyp_manager.egg-info/entry_points.txt
pyp_manager.egg-info/top_level.txt